counter.v
// file: count.v
// author: @amrgouhar

`timescale 1ns/1ns

module counter(clk, rst, newcount, outcount);
    input clk;
    input rst;
    input newcount;
    output outcount;
    
    reg en;
    
    reg[2:0] counter;
    
    assign outcount = (counter == 3'b111);
    
    always @(posedge clk or negedge rst) begin
        if(!rst) begin
            counter <=3'b000;
            en<=1'b0;
        end
        else 
            if(newcount) begin
                counter <=3'b000;
                en <= 1'b1;
            end
            else
                if(en) begin
                    counter <= counter + 3'b001;
                    if(counter == 3'b111) begin
                        en <= 1'b0;
                    end
                end
                else 
                    counter <= counter;
    end
    
endmodule

counter_tb.v
// file: counter_tb.v
// author: @amrgouhar
// Testbench for counter

`timescale 1ns/1ns

module counter_tb;

	//Inputs
	reg clk;
	reg rst;
	reg newcount;


	//Outputs
	wire outcount;


	//Instantiation of Unit Under Test
	counter uut (
		.clk(clk),
		.rst(rst),
		.newcount(newcount),
		.outcount(outcount)
	);

always #5 clk = ~clk;
	initial begin
	//Inputs initialization
		clk = 0;
		rst = 0;
		newcount = 0;
        #10 rst =1;
        #15 newcount = 1;
        #5 newcount = 0;
        #25 newcount = 1;
        #5 newcount = 0;
        #105 newcount = 1;
        #5 newcount = 0;

	//Wait for the reset
		#100;

	end

endmodule

build (read-only)/counter_tb.vcd
$date
	Sat Feb 24 08:33:06 2018
$end
$version
	Icarus Verilog
$end
$timescale
	1ns
$end
$scope module counter_tb $end
$var wire 1 ! outcount $end
$var reg 1 " clk $end
$var reg 1 # newcount $end
$var reg 1 $ rst $end
$scope module uut $end
$var wire 1 " clk $end
$var wire 1 # newcount $end
$var wire 1 $ rst $end
$var wire 1 ! outcount $end
$var reg 3 % counter [2:0] $end
$var reg 1 & en $end
$upscope $end
$upscope $end
$enddefinitions $end
#0
$dumpvars
0&
b0 %
0$
0#
0"
0!
$end
#5
1"
#10
0"
1$
#15
1"
#20
0"
#25
1&
1"
1#
#30
0"
0#
#35
b1 %
1"
#40
0"
#45
b10 %
1"
#50
0"
#55
b0 %
1"
1#
#60
0"
0#
#65
b1 %
1"
#70
0"
#75
b10 %
1"
#80
0"
#85
b11 %
1"
#90
0"
#95
b100 %
1"
#100
0"
#105
b101 %
1"
#110
0"
#115
b110 %
1"
#120
0"
#125
1!
b111 %
1"
#130
0"
#135
0&
0!
b0 %
1"
#140
0"
#145
1"
#150
0"
#155
1"
#160
0"
#165
1&
1"
1#
#170
0"
0#
#175
b1 %
1"
#180
0"
#185
b10 %
1"
#190
0"
#195
b11 %
1"
#200
0"
#205
b100 %
1"
#210
0"
#215
b101 %
1"
#220
0"
#225
b110 %
1"
#230
0"
#235
1!
b111 %
1"
#240
0"
#245
0&
0!
b0 %
1"
