The Module/DU.v
// file: DU.v
// author: @amrgouhar

`timescale 1ns/1ns

module DU(clk, rst,dbit,go,Data, oSDA);
input clk;
input rst;
input dbit;
input go;
input [7:0] Data;
output reg oSDA;

reg [7:0]dout;

    always @(posedge clk or negedge rst or posedge go) begin
        if(!rst) begin
            dout <= 8'bx;
            oSDA <= 1'b0;
        end
        else begin
            if(go) begin
                dout <= Data;
            end
            else if(dbit) begin
                oSDA <= dout[0];
                dout <= dout >>1;
            end
        end
    end
endmodule

src/DU_tb.v
// file: DU_tb.v
// author: @amrgouhar
// Testbench for DU

`timescale 1ns/1ns

module DU_tb;

	//Inputs
	reg clk;
	reg rst;
	reg dbit;
	reg go;
	reg [7: 0] Data;


	//Outputs
	wire oSDA;


	//Instantiation of Unit Under Test
	DU uut (
		.clk(clk),
		.rst(rst),
		.dbit(dbit),
		.go(go),
		.Data(Data),
		.oSDA(oSDA)
	);



always #5 clk = ~clk;
	initial begin
	//Inputs initialization
		clk = 0;
		rst = 0;
		dbit = 0;
		go = 0;
		Data = 0;
        #15 rst = 1;
        #10 Data= 123;
        #10 go = 1;
        #10 go =0;
            dbit = 1;
        #80 dbit =0;

	//Wait for the reset
		#100;

	end
endmodule

build (read-only)/DU_tb.vcd
$date
	Sat Feb 24 17:56:25 2018
$end
$version
	Icarus Verilog
$end
$timescale
	1ns
$end
$scope module DU_tb $end
$var wire 1 ! oSDA $end
$var reg 8 " Data [7:0] $end
$var reg 1 # clk $end
$var reg 1 $ dbit $end
$var reg 1 % go $end
$var reg 1 & rst $end
$scope module uut $end
$var wire 8 ' Data [7:0] $end
$var wire 1 # clk $end
$var wire 1 $ dbit $end
$var wire 1 % go $end
$var wire 1 & rst $end
$var reg 8 ( dout [7:0] $end
$var reg 1 ! oSDA $end
$upscope $end
$upscope $end
$enddefinitions $end
#0
$dumpvars
bx (
b0 '
0&
0%
0$
0#
b0 "
0!
$end
#5
1#
#10
0#
#15
1#
1&
#20
0#
#25
1#
b1111011 "
b1111011 '
#30
0#
#35
b1111011 (
1#
1%
#40
0#
#45
b111101 (
1!
1#
1$
0%
#50
0#
#55
b11110 (
1#
#60
0#
#65
b1111 (
0!
1#
#70
0#
#75
b111 (
1!
1#
#80
0#
#85
b11 (
1#
#90
0#
#95
b1 (
1#
#100
0#
#105
b0 (
1#
#110
0#
#115
0!
1#
#120
0#
#125
1#
0$
