The Module/MasterControl.v
// file: MasterControl.v
// author: @amrgouhar

`timescale 1ns/1ns

module MasterControl(clk, rst, iSDA, bit8, go, busy, newcount, dbit, abit, done, success, en, sel);
input clk;
input rst;
input iSDA;
input bit8;
input go;
output reg busy;
output reg newcount;
output reg dbit;
output reg abit;
output reg done;
output reg success;
output reg en;
output reg [1:0] sel;

reg countStarted;


reg [2:0] state, next_state;
parameter [2:0] idle=3'b000, start=3'b001, sendAddr=3'b010, Addrsent =3'b011, sendData = 3'b100, Datasent = 3'b101, Success = 3'b110;
/*
always @(state or go or bit8 or iSDA) begin
    case(state)
        idle: if(go) next_state = start;
            else    next_state = idle;
            
        start:  next_state= sendAddr;
        
        sendAddr: if(bit8) next_state = Addrsent;
            else next_state = sendAddr;
            
        Addrsent: if(iSDA) next_state = sendData;
            else  begin next_state = idle; back = 1'b1; end
            
        sendData: if(bit8) next_state = Datasent;
            else next_state = sendData;
        Datasent:   if(iSDA) next_state = Success;
            else begin   next_state = idle; back = 1'b1; end
        Success: begin next_state = idle; back = 1'b1; end
    endcase
end

always @(posedge clk or negedge rst) begin
    if(!rst) begin
        state = idle;
    end
    else begin 
      state = next_state;
      done = back;
    end
end
*/
reg[1:0] cnt;

always @(posedge clk or negedge rst) begin
    if(!rst) begin
        state = idle;
    end
    else begin 
          case(state)
        idle: if(go) begin state = start; end
            else    state = idle;
            
        start:  begin state= sendAddr; en = 1'b1; end
        
        sendAddr: if(bit8) begin state = Addrsent; en = 1'b0; end
            else state = sendAddr;
            
        Addrsent: if(cnt <= 2'b01) state = Addrsent;
                    else
            
            if(iSDA) begin state = sendData; en = 1'b1;end
            else begin state = idle; done = 1'b1; end
            
        sendData: if(bit8) begin  state = Datasent; en = 1'b0; end
            else state = sendData;
        Datasent:   if(cnt <= 2'b01) state = Datasent;
                    else
             
            if(iSDA) begin state = Success; en = 1'b1; end
            else begin   state = idle; done = 1'b1; end
        Success:  if(cnt == 2'b00) 
            begin state = idle; done = 1'b1; end
    endcase

    end
end


always @(posedge clk or negedge rst) begin
    if(!rst) begin
        busy = 1'b0;
        newcount = 1'b0;
        dbit = 1'b0;
        abit = 1'b0;
        done = 1'b0;
        success=1'b0;
        sel = 2'b11;
        en = 1'b0;
        countStarted = 1'b0;
        cnt = 2'b00;
    end
    else
        case(state)
        idle: begin 
                busy = 1'b0;
                newcount = 1'b0;
                dbit = 1'b0;
                abit = 1'b0;
                done = 1'b0;
                success=1'b0;
                countStarted = 1'b0;
                sel = 2'b11;
                cnt = 2'b00;
            end
        start:begin 
            busy = 1'b1;
            sel = 2'b00;
            end
        sendAddr: begin
            abit = 1'b1;
            sel = 2'b01;
            if(countStarted)
                newcount = 1'b0;
            else begin
                newcount = 1'b1;
                countStarted = 1'b1;
            end       
            cnt = 2'd0;
        end
        Addrsent:begin
            countStarted =1'b0;
            abit = 1'b0;
            sel = 2'b11;
            cnt = cnt+2'd1;
            end
        sendData:begin
            dbit = 1'b1;
            sel = 2'b10;
            if(countStarted)
                newcount = 1'b0;
            else begin
                newcount = 1'b1;
                countStarted = 1'b1;
            end       
            cnt = 2'd0;
            end
        Datasent:begin
            countStarted =1'b0;
            abit = 1'b0;
            sel = 2'b11;
            cnt = cnt+2'd1;
            end
        Success:begin
            success = 1'b1;
            busy = 1'b0;
            cnt = cnt+2'd1;
            end

        endcase
end

endmodule

The Module/DU.v
// file: DU.v
// author: @amrgouhar

`timescale 1ns/1ns

module DU(clk, rst,dbit,go,Data, oSDA);
input clk;
input rst;
input dbit;
input go;
input [7:0] Data;
output reg oSDA;

reg [7:0]dout;

    always @(posedge clk or negedge rst or posedge go) begin
        if(!rst) begin
            dout <= 8'bx;
            oSDA <= 1'b0;
        end
        else begin
            if(go) begin
                dout <= Data;
            end
            else if(dbit) begin
                oSDA <= dout[0];
                dout <= dout >>1;
            end
        end
    end
endmodule

The Module/AU.v
// file: AU.v
// author: @amrgouhar

`timescale 1ns/1ns

module AU(clk, rst,abit,go,addrIn, oSDA);
input clk;
input rst;
input abit;
input go;
input [6:0] addrIn;
output reg oSDA;

reg [7:0]addr;
wire R_W = 1'b0;        //here we fix read/write to write, because we handle write only

    always @(posedge clk or negedge rst or posedge go) begin
        if(!rst) begin
            addr <= 8'bx;
            oSDA <= 1'b0;
        end
        else begin
            if(go) begin
                addr <= {R_W,addrIn};
            end
            else if(abit) begin
                oSDA <= addr[0];
                addr <= addr >>1;
            end
        end
    end
endmodule

counter.v
// file: count.v
// author: @amrgouhar

`timescale 1ns/1ns

module counter(clk, rst, newcount, outcount);
    input clk;
    input rst;
    input newcount;
    output outcount;
    
    reg en;
    
    reg[2:0] counter;
    
    assign outcount = (counter == 3'b111);
    
    always @(posedge clk or negedge rst) begin
        if(!rst) begin
            counter <=3'b000;
            en<=1'b0;
        end
        else 
            if(newcount) begin
                counter <=3'b000;
                en <= 1'b1;
            end
            else
                if(en) begin
                    counter <= counter + 3'b001;
                    if(counter == 3'b111) begin
                        en <= 1'b0;
                    end
                end
                else 
                    counter <= counter;
    end
    
endmodule

The Module/BIU.v
// file: BIU.v
// author: @amrgouhar

`timescale 1ns/1ns

module BIU(iSCL, oSDA,SCL,SDA,iSDA, en, clk);
input iSCL;
input oSDA;
input en;
inout SDA;
output SCL;
output reg iSDA;
output clk;

reg mid;

assign clk = iSCL;
assign SCL = iSCL;

assign SDA = en? mid:1'bz;


always @(posedge iSCL)
    if(!en) begin
        iSDA <= SDA;
        mid <= 1'bz;
    end
    else begin
        iSDA <= 1'bz;
        mid <= oSDA;
        end
endmodule

The Module/SSU.v
// file: SSU.v
// author: @amrgouhar

`timescale 1ns/1ns

module SSU(busy, mclk, rst, iSCL, oSDA);
    input busy;
    input mclk;
    input rst;
    output reg iSCL;
    output reg oSDA;
    
reg [2:0] state, next_state;
parameter [2:0] idle=3'b000, startC=3'b001, stopC=3'b010, zero =3'b011, one = 3'b100;

always @(state or busy) begin
    case(state)
        idle: if(busy) next_state = startC;
            else    next_state = idle;
        startC:  if(busy) next_state= one;
            else    next_state = stopC;
        one: if(busy) next_state = one;
            else next_state = stopC;
        stopC:   if(busy) next_state = startC;
            else    next_state = stopC;
    endcase
end

always @(posedge mclk or negedge rst) begin
    if(!rst) begin
        state = idle;
    end
    else begin 
      state = next_state;
    end
end

always @(posedge mclk or negedge rst) begin
    if(!rst) begin
        iSCL = 1'b1;
        oSDA = 1'b0;
    end
    else
        case(next_state)
        idle: begin 
            iSCL = 1'b1;
            oSDA = 1'b0;
            end
        startC:begin 
            iSCL = ~iSCL;
            oSDA = 1'b1;
            end
        one: begin
            iSCL = ~iSCL;
            oSDA = 1'b0;
        end
        stopC:begin
            iSCL =1'b1;
            oSDA = 1'b0;
            end
        endcase
end
    
endmodule

The Module/I2CBus.v
// file: I2CBus.v
// author: @amrgouhar

`timescale 1ns/1ns

module I2CBus(SCL, SDA, mclk, rst, go,addrIn,Data,done, success, enb, bitx);

inout SDA;

input mclk;
input rst;
input go;
input [6:0] addrIn;
input [7:0] Data;

output done;
output success;
output SCL;

// for simulation
output enb;        
output bitx;

wire busy;
wire iSCL;
wire oSDAssu;   //00
wire iSDA;
wire clk;
wire newcount;
wire bit8;
wire abit;
wire dbit;
wire oSDAau;    //01
wire oSDAdu;    //10
wire oSDA;      //select;

wire [1:0] sel; 

wire en;        //add to master controller

//for simulation
assign enb = en;
assign bitx = bit8;

assign oSDA = (sel == 2'b00)? oSDAssu:(sel == 2'b01)? oSDAau:(sel == 2'b10)? oSDAdu:1'bz;

// systemClk ssclk(.mclk(mclk),.clk(clk),.rst(rst));

SSU ssu(.busy(busy), .mclk(mclk), .rst(rst), .iSCL(iSCL), .oSDA(oSDAssu));

BIU biu(.iSCL(iSCL), .oSDA(oSDA),.SCL(SCL),.SDA(SDA),.iSDA(iSDA), .en(en), .clk(clk));

counter cnt(.clk(clk), .rst(rst), .newcount(newcount), .outcount(bit8));

AU au(.clk(clk), .rst(rst),.abit(abit),.go(go),.addrIn(addrIn), .oSDA(oSDAau));

DU du(.clk(clk), .rst(rst),.dbit(dbit),.go(go),.Data(Data), .oSDA(oSDAdu));

MasterControl mc(.clk(mclk), .rst(rst), .iSDA(iSDA), .bit8(bit8), .go(go), .busy(busy), .newcount(newcount), .dbit(dbit), .abit(abit), .done(done), .success(success), .en(en),.sel(sel));

endmodule

The Module/I2CBus_tb.v
// file: I2CBus_tb.v
// author: @amrgouhar
// Testbench for I2CBus

`timescale 1ns/1ns

module I2CBus_tb;

	//Inputs
	reg mclk;
	reg rst;
	reg go;
	reg [6: 0] addrIn;
	reg [7: 0] Data;


	//Outputs
	wire done;
	wire success;
	wire SCL;
    
    //simulation
    wire enb;
    wire bitx;
    
    //inout
    wire input_value;
    reg output_value;
    wire SDA;


	//Instantiation of Unit Under Test
	I2CBus uut (
		.mclk(mclk),
		.rst(rst),
		.go(go),
		.addrIn(addrIn),
		.Data(Data),
		.done(done),
		.success(success),
		.SCL(SCL),
		.SDA(SDA),
		.enb(enb),
		.bitx(bitx)
	);


    assign input_value = (enb)? SDA: 1'bz;
    assign SDA = (~enb)? output_value : 1'bz;

always #5 mclk = ~mclk;
	initial begin
	//Inputs initialization
		mclk = 0;
		rst = 0;
		go = 0;
		addrIn = 0;
		Data = 0;
		repeat(20) begin
		rst = 0;
        #15 rst = 1;
        #5 addrIn = $random % 255;
        Data = $random % 255;
        #5 go =1;
        #20 go = 0;
        #500;
        end       
	//Wait for the reset
		#100;
	end

 always@(posedge mclk) begin
            if(bitx)
                output_value = 1'b1;
            else
                output_value = 1'b0;
        end

   always @(posedge done)
    begin
            if(success)
                begin
                    #5;
                $display("Success");
            end
            else begin
                #5;
                $display("Failure");
            end
    end



endmodule

build (read-only)/I2CBus_tb.vcd
$date
	Mon Feb 26 19:55:16 2018
$end
$version
	Icarus Verilog
$end
$timescale
	1ns
$end
$scope module I2CBus_tb $end
$var wire 1 ! SDA $end
$var wire 1 " success $end
$var wire 1 # input_value $end
$var wire 1 $ enb $end
$var wire 1 % done $end
$var wire 1 & bitx $end
$var wire 1 ' SCL $end
$var reg 8 ( Data [7:0] $end
$var reg 7 ) addrIn [6:0] $end
$var reg 1 * go $end
$var reg 1 + mclk $end
$var reg 1 , output_value $end
$var reg 1 - rst $end
$scope module uut $end
$var wire 8 . Data [7:0] $end
$var wire 1 ! SDA $end
$var wire 7 / addrIn [6:0] $end
$var wire 1 & bitx $end
$var wire 1 $ enb $end
$var wire 1 * go $end
$var wire 1 + mclk $end
$var wire 1 - rst $end
$var wire 1 " success $end
$var wire 2 0 sel [1:0] $end
$var wire 1 1 oSDAssu $end
$var wire 1 2 oSDAdu $end
$var wire 1 3 oSDAau $end
$var wire 1 4 oSDA $end
$var wire 1 5 newcount $end
$var wire 1 6 iSDA $end
$var wire 1 7 iSCL $end
$var wire 1 8 en $end
$var wire 1 % done $end
$var wire 1 9 dbit $end
$var wire 1 : clk $end
$var wire 1 ; busy $end
$var wire 1 < bit8 $end
$var wire 1 = abit $end
$var wire 1 ' SCL $end
$scope module au $end
$var wire 1 > R_W $end
$var wire 7 ? addrIn [6:0] $end
$var wire 1 * go $end
$var wire 1 - rst $end
$var wire 1 : clk $end
$var wire 1 = abit $end
$var reg 8 @ addr [7:0] $end
$var reg 1 3 oSDA $end
$upscope $end
$scope module biu $end
$var wire 1 ' SCL $end
$var wire 1 ! SDA $end
$var wire 1 : clk $end
$var wire 1 4 oSDA $end
$var wire 1 7 iSCL $end
$var wire 1 8 en $end
$var reg 1 6 iSDA $end
$var reg 1 A mid $end
$upscope $end
$scope module cnt $end
$var wire 1 : clk $end
$var wire 1 - rst $end
$var wire 1 < outcount $end
$var wire 1 5 newcount $end
$var reg 3 B counter [2:0] $end
$var reg 1 C en $end
$upscope $end
$scope module du $end
$var wire 8 D Data [7:0] $end
$var wire 1 : clk $end
$var wire 1 * go $end
$var wire 1 - rst $end
$var wire 1 9 dbit $end
$var reg 8 E dout [7:0] $end
$var reg 1 2 oSDA $end
$upscope $end
$scope module mc $end
$var wire 1 < bit8 $end
$var wire 1 + clk $end
$var wire 1 * go $end
$var wire 1 6 iSDA $end
$var wire 1 - rst $end
$var reg 1 = abit $end
$var reg 1 ; busy $end
$var reg 2 F cnt [1:0] $end
$var reg 1 G countStarted $end
$var reg 1 9 dbit $end
$var reg 1 % done $end
$var reg 1 8 en $end
$var reg 1 5 newcount $end
$var reg 2 H sel [1:0] $end
$var reg 3 I state [2:0] $end
$var reg 1 " success $end
$upscope $end
$scope module ssu $end
$var wire 1 ; busy $end
$var wire 1 + mclk $end
$var wire 1 - rst $end
$var reg 1 7 iSCL $end
$var reg 3 J next_state [2:0] $end
$var reg 1 1 oSDA $end
$var reg 3 K state [2:0] $end
$upscope $end
$upscope $end
$upscope $end
$enddefinitions $end
#0
$dumpvars
b0 K
b0 J
b0 I
b11 H
0G
b0 F
bx E
b0 D
0C
b0 B
zA
bx @
b0 ?
0>
0=
0<
0;
1:
09
08
17
x6
05
z4
03
02
01
b11 0
b0 /
b0 .
0-
x,
0+
0*
b0 )
b0 (
1'
0&
0%
0$
z#
0"
x!
$end
#5
0!
0,
1+
#10
0+
#15
1+
1-
#20
0+
b101010 (
b101010 .
b101010 D
#25
b101010 E
b0 @
04
b1 J
b0 0
b0 H
1;
b1 I
1+
1*
#30
0+
#35
z!
b100 J
14
z#
b1 K
11
0'
0:
07
1$
18
b10 I
1+
#40
0+
#45
1#
1!
1C
1A
z6
04
1G
15
b1 0
b1 H
1=
01
1'
1:
17
b100 K
1+
0*
#50
0+
#55
0'
0:
07
05
1+
#60
0+
#65
0#
0!
b1 B
0A
1'
1:
17
1+
#70
0+
#75
0'
0:
07
1+
#80
0+
#85
b10 B
1'
1:
17
1+
#90
0+
#95
0'
0:
07
1+
#100
0+
#105
b11 B
1'
1:
17
1+
#110
0+
#115
0'
0:
07
1+
#120
0+
#125
b100 B
1'
1:
17
1+
#130
0+
#135
0'
0:
07
1+
#140
0+
#145
b101 B
1'
1:
17
1+
#150
0+
#155
0'
0:
07
1+
#160
0+
#165
b110 B
1'
1:
17
1+
#170
0+
#175
0'
0:
07
1+
#180
0+
#185
1&
1<
b111 B
1'
1:
17
1+
#190
0+
#195
1!
z#
0'
0:
07
0$
08
b11 I
1,
1+
#200
0+
#205
0C
0&
0<
b0 B
zA
16
z4
b1 F
b11 0
b11 H
0=
0G
1'
1:
17
1+
#210
0+
#215
z#
z!
0'
0:
07
1$
18
b100 I
b10 F
0,
1+
#220
0+
#225
b10101 E
1C
z6
04
b0 F
1G
15
b10 0
b10 H
19
1'
1:
17
1+
#230
0+
#235
0'
0:
07
05
1+
#240
0+
#245
14
0#
0!
b1010 E
12
b1 B
0A
1'
1:
17
1+
#250
0+
#255
0'
0:
07
1+
#260
0+
#265
04
1#
1!
b101 E
02
b10 B
1A
1'
1:
17
1+
#270
0+
#275
0'
0:
07
1+
#280
0+
#285
14
0#
0!
b10 E
12
b11 B
0A
1'
1:
17
1+
#290
0+
#295
0'
0:
07
1+
#300
0+
#305
04
1#
1!
b1 E
02
b100 B
1A
1'
1:
17
1+
#310
0+
#315
0'
0:
07
1+
#320
0+
#325
14
0#
0!
b0 E
12
b101 B
0A
1'
1:
17
1+
#330
0+
#335
0'
0:
07
1+
#340
0+
#345
04
1#
1!
02
b110 B
1A
1'
1:
17
1+
#350
0+
#355
0'
0:
07
1+
#360
0+
#365
0#
0!
1&
1<
b111 B
0A
1'
1:
17
1+
#370
0+
#375
1!
z#
0'
0:
07
0$
08
b101 I
1,
1+
#380
0+
#385
0C
0&
0<
b0 B
zA
16
z4
b1 F
b11 0
b11 H
0G
1'
1:
17
1+
#390
0+
#395
z#
z!
0'
0:
07
1$
18
b110 I
b10 F
0,
1+
#400
0+
#405
z6
b10 J
b11 F
0;
1"
1'
1:
17
1+
#410
0+
#415
b10 K
1%
b0 I
b0 F
1+
#420
0+
#425
0"
0%
09
1+
#430
0+
#435
1+
#440
0+
#445
1+
#450
0+
#455
1+
#460
0+
#465
1+
#470
0+
#475
1+
#480
0+
#485
1+
#490
0+
#495
1+
#500
0+
#505
1+
#510
0+
#515
1+
#520
0+
#525
1+
#530
0+
#535
1+
#540
0+
#545
bx E
bx @
0!
b0 J
0$
08
b0 K
1+
0-
#550
0+
#555
1+
#560
0+
1-
#565
1+
b1011100 (
b1011100 .
b1011100 D
b1101000 )
b1101000 /
b1101000 ?
#570
b1101000 @
b1011100 E
0+
1*
#575
b1 I
1+
#580
0+
#585
04
z!
z#
1G
15
b1 0
b1 H
1=
1$
18
b10 I
1+
#590
0+
0*
#595
05
1+
