The Module/SSU.v
// file: SSU.v
// author: @amrgouhar

`timescale 1ns/1ns

module SSU(busy, mclk, rst, iSCL, oSDA);
    input busy;
    input mclk;
    input rst;
    output reg iSCL;
    output reg oSDA;
    
reg [2:0] state, next_state;
parameter [2:0] idle=3'b000, startC=3'b001, stopC=3'b010, zero =3'b011, one = 3'b100;

always @(state or busy) begin
    case(state)
        idle: if(busy) next_state = startC;
            else    next_state = idle;
        startC:  if(busy) next_state= one;
            else    next_state = stopC;
        one: if(busy) next_state = one;
            else next_state = stopC;
        stopC:   if(busy) next_state = startC;
            else    next_state = stopC;
    endcase
end

always @(posedge mclk or negedge rst) begin
    if(!rst) begin
        state = idle;
    end
    else begin 
      state = next_state;
    end
end

always @(posedge mclk or negedge rst) begin
    if(!rst) begin
        iSCL = 1'b1;
        oSDA = 1'b0;
    end
    else
        case(next_state)
        idle: begin 
            iSCL = 1'b1;
            oSDA = 1'b0;
            end
        startC:begin 
            iSCL = ~iSCL;
            oSDA = 1'b1;
            end
        one: begin
            iSCL = ~iSCL;
            oSDA = 1'b0;
        end
        stopC:begin
            iSCL =1'b1;
            oSDA = 1'b0;
            end
        endcase
end
    
endmodule

src/SSU_tb.v
// file: SSU_tb.v
// author: @amrgouhar
// Testbench for SSU

`timescale 1ns/1ns

module SSU_tb;

	//Inputs
	reg busy;
	reg mclk;
	reg rst;


	//Outputs
	wire iSCL;
	wire oSDA;


	//Instantiation of Unit Under Test
	SSU uut (
		.busy(busy),
		.mclk(mclk),
		.rst(rst),
		.iSCL(iSCL),
		.oSDA(oSDA)
	);

    always #5 mclk = ~ mclk;
	initial begin
	//Inputs initialization
		busy = 0;
		mclk = 0;
		rst = 0;
        #15 rst = 1;
        #10 busy = 1;
        #50 busy = 0;
        #100 busy = 1;

	//Wait for the reset
		#100;

	end

endmodule

build (read-only)/SSU_tb.vcd
$date
	Sat Feb 24 15:46:59 2018
$end
$version
	Icarus Verilog
$end
$timescale
	1ns
$end
$scope module SSU_tb $end
$var wire 1 ! oSDA $end
$var wire 1 " iSCL $end
$var reg 1 # busy $end
$var reg 1 $ mclk $end
$var reg 1 % rst $end
$scope module uut $end
$var wire 1 # busy $end
$var wire 1 $ mclk $end
$var wire 1 % rst $end
$var reg 1 " iSCL $end
$var reg 3 & next_state [2:0] $end
$var reg 1 ! oSDA $end
$var reg 3 ' state [2:0] $end
$upscope $end
$upscope $end
$enddefinitions $end
#0
$dumpvars
b0 '
b0 &
0%
0$
0#
1"
0!
$end
#5
1$
#10
0$
#15
1$
1%
#20
0$
#25
1!
0"
b1 '
b100 &
1$
1#
#30
0$
#35
b100 '
0!
1"
1$
#40
0$
#45
0"
1$
#50
0$
#55
1"
1$
#60
0$
#65
0"
1$
#70
0$
#75
b10 '
1"
b10 &
1$
0#
#80
0$
#85
1$
#90
0$
#95
1$
#100
0$
#105
1$
#110
0$
#115
1$
#120
0$
#125
1$
#130
0$
#135
1$
#140
0$
#145
1$
#150
0$
#155
1$
#160
0$
#165
1$
#170
0$
#175
b1 '
1!
0"
b100 &
1$
1#
#180
0$
#185
0!
1"
b100 '
1$
#190
0$
#195
0"
1$
#200
0$
#205
1"
1$
#210
0$
#215
0"
1$
#220
0$
#225
1"
1$
#230
0$
#235
0"
1$
#240
0$
#245
1"
1$
#250
0$
#255
0"
1$
#260
0$
#265
1"
1$
#270
0$
#275
0"
1$
#280
0$
#285
1"
1$
#290
0$
#295
0"
1$
#300
0$
#305
1"
1$
#310
0$
#315
0"
1$
#320
0$
#325
1"
1$
#330
0$
#335
0"
1$
#340
0$
#345
1"
1$
#350
0$
#355
0"
1$
#360
0$
#365
1"
1$
#370
0$
#375
0"
1$
#380
0$
#385
1"
1$
#390
0$
#395
0"
1$
#400
0$
#405
1"
1$
#410
0$
#415
0"
1$
#420
0$
#425
1"
1$
#430
0$
#435
0"
1$
#440
0$
#445
1"
1$
#450
0$
#455
0"
1$
#460
0$
#465
1"
1$
#470
0$
#475
0"
1$
#480
0$
#485
1"
1$
#490
0$
#495
0"
1$
#500
0$
#505
1"
1$
#510
0$
#515
0"
1$
#520
0$
#525
1"
1$
#530
0$
#535
0"
1$
#540
0$
#545
1"
1$
#550
0$
#555
0"
1$
#560
0$
#565
1"
1$
#570
0$
#575
0"
1$
#580
0$
#585
1"
1$
#590
0$
#595
0"
1$
#600
0$
#605
1"
1$
#610
0$
#615
0"
1$
#620
0$
#625
1"
1$
#630
0$
#635
0"
1$
#640
0$
#645
1"
1$
#650
0$
#655
0"
1$
#660
0$
#665
1"
1$
#670
0$
#675
0"
1$
#680
0$
#685
1"
1$
#690
0$
#695
0"
1$
#700
0$
#705
1"
1$
#710
0$
#715
0"
1$
#720
0$
#725
1"
1$
#730
0$
#735
0"
1$
#740
0$
#745
1"
1$
#750
0$
#755
0"
1$
#760
0$
#765
1"
1$
#770
0$
#775
0"
1$
#780
0$
#785
1"
1$
#790
0$
#795
0"
1$
#800
0$
#805
1"
1$
#810
0$
#815
0"
1$
#820
0$
#825
1"
1$
#830
0$
#835
0"
1$
#840
0$
#845
1"
1$
#850
0$
#855
0"
1$
#860
0$
#865
1"
1$
#870
0$
#875
0"
1$
#880
0$
#885
1"
1$
#890
0$
#895
0"
1$
#900
0$
#905
1"
1$
#910
0$
#915
0"
1$
#920
0$
#925
1"
1$
#930
0$
#935
0"
1$
#940
0$
#945
1"
1$
#950
0$
#955
0"
1$
#960
0$
#965
1"
1$
#970
0$
#975
0"
1$
#980
0$
#985
1"
1$
#990
0$
#995
0"
1$
